{
  "DataContractVersion": "1.1",
  "DocumentTypes": [
    {
      "DocumentTypeId": "NoGroup.NoCategory.BienLai",
      "Group": "",
      "Category": "",
      "Name": "BienLai",
      "OptionalUniqueIdentifier": "",
      "TypeField": {
        "FieldId": "NoGroup.NoCategory.BienLai.DocumentType",
        "FieldName": "Document Type"
      },
      "Fields": [
        {
          "FieldId": "NoGroup.NoCategory.BienLai.Form",
          "FieldName": "Form",
          "IsMultiValue": false,
          "Type": "Text",
          "DeriveFieldsFormat": "",
          "Components": [],
          "SetValues": [],
          "Metadata": [
            {
              "Key": "Color",
              "Value": "#038a18"
            },
            {
              "Key": "Hotkey",
              "Value": "r"
            }
          ],
          "RuleSet": null
        },
        {
          "FieldId": "NoGroup.NoCategory.BienLai.Serial",
          "FieldName": "Serial",
          "IsMultiValue": false,
          "Type": "Text",
          "DeriveFieldsFormat": "",
          "Components": [],
          "SetValues": [],
          "Metadata": [
            {
              "Key": "Color",
              "Value": "#fa6616"
            },
            {
              "Key": "Hotkey",
              "Value": "e"
            }
          ],
          "RuleSet": null
        },
        {
          "FieldId": "NoGroup.NoCategory.BienLai.No",
          "FieldName": "No.",
          "IsMultiValue": false,
          "Type": "Text",
          "DeriveFieldsFormat": "",
          "Components": [],
          "SetValues": [],
          "Metadata": [
            {
              "Key": "Color",
              "Value": "#8a97a0"
            },
            {
              "Key": "Hotkey",
              "Value": "q"
            }
          ],
          "RuleSet": null
        },
        {
          "FieldId": "NoGroup.NoCategory.BienLai.NameCustomer",
          "FieldName": "Name Customer",
          "IsMultiValue": false,
          "Type": "Text",
          "DeriveFieldsFormat": "",
          "Components": [],
          "SetValues": [],
          "Metadata": [
            {
              "Key": "Color",
              "Value": "#4e22f0"
            },
            {
              "Key": "Hotkey",
              "Value": "m"
            }
          ],
          "RuleSet": null
        },
        {
          "FieldId": "NoGroup.NoCategory.BienLai.AddressCustomer",
          "FieldName": "Address Customer",
          "IsMultiValue": false,
          "Type": "Address",
          "DeriveFieldsFormat": "",
          "Components": [],
          "SetValues": [],
          "Metadata": [
            {
              "Key": "Color",
              "Value": "#4893db"
            },
            {
              "Key": "Hotkey",
              "Value": "c"
            }
          ],
          "RuleSet": null
        },
        {
          "FieldId": "NoGroup.NoCategory.BienLai.PaymentTotal",
          "FieldName": "Payment Total",
          "IsMultiValue": false,
          "Type": "Number",
          "DeriveFieldsFormat": "",
          "Components": [],
          "SetValues": [],
          "Metadata": [
            {
              "Key": "Color",
              "Value": "#3ddb77"
            },
            {
              "Key": "Hotkey",
              "Value": "y"
            }
          ],
          "RuleSet": null
        },
        {
          "FieldId": "NoGroup.NoCategory.BienLai.SignaturevalidIssued",
          "FieldName": "Signature valid Issued",
          "IsMultiValue": false,
          "Type": "Boolean",
          "DeriveFieldsFormat": "",
          "Components": [],
          "SetValues": [],
          "Metadata": [
            {
              "Key": "Color",
              "Value": "#cf9a38"
            },
            {
              "Key": "Hotkey",
              "Value": "g"
            }
          ],
          "RuleSet": null
        }
      ]
    },
    {
      "DocumentTypeId": "NoGroup.NoCategory.PhiThue",
      "Group": "",
      "Category": "",
      "Name": "PhiThue",
      "OptionalUniqueIdentifier": "",
      "TypeField": {
        "FieldId": "NoGroup.NoCategory.PhiThue.DocumentType",
        "FieldName": "Document Type"
      },
      "Fields": [
        {
          "FieldId": "NoGroup.NoCategory.PhiThue.Form",
          "FieldName": "Form",
          "IsMultiValue": false,
          "Type": "Text",
          "DeriveFieldsFormat": "",
          "Components": [],
          "SetValues": [],
          "Metadata": [
            {
              "Key": "Color",
              "Value": "#038a18"
            },
            {
              "Key": "Hotkey",
              "Value": "r"
            }
          ],
          "RuleSet": null
        },
        {
          "FieldId": "NoGroup.NoCategory.PhiThue.Serial",
          "FieldName": "Serial",
          "IsMultiValue": false,
          "Type": "Text",
          "DeriveFieldsFormat": "",
          "Components": [],
          "SetValues": [],
          "Metadata": [
            {
              "Key": "Color",
              "Value": "#fa6616"
            },
            {
              "Key": "Hotkey",
              "Value": "e"
            }
          ],
          "RuleSet": null
        },
        {
          "FieldId": "NoGroup.NoCategory.PhiThue.No",
          "FieldName": "No.",
          "IsMultiValue": false,
          "Type": "Text",
          "DeriveFieldsFormat": "",
          "Components": [],
          "SetValues": [],
          "Metadata": [
            {
              "Key": "Color",
              "Value": "#8a97a0"
            },
            {
              "Key": "Hotkey",
              "Value": "q"
            }
          ],
          "RuleSet": null
        },
        {
          "FieldId": "NoGroup.NoCategory.PhiThue.NameCustomer",
          "FieldName": "Name Customer",
          "IsMultiValue": false,
          "Type": "Text",
          "DeriveFieldsFormat": "",
          "Components": [],
          "SetValues": [],
          "Metadata": [
            {
              "Key": "Color",
              "Value": "#d2d550"
            },
            {
              "Key": "Hotkey",
              "Value": "m"
            }
          ],
          "RuleSet": null
        },
        {
          "FieldId": "NoGroup.NoCategory.PhiThue.TaxCodeCustomer",
          "FieldName": "Tax Code Customer",
          "IsMultiValue": false,
          "Type": "Number",
          "DeriveFieldsFormat": "",
          "Components": [],
          "SetValues": [],
          "Metadata": [
            {
              "Key": "Color",
              "Value": "#6eb84a"
            },
            {
              "Key": "Hotkey",
              "Value": "x"
            }
          ],
          "RuleSet": null
        },
        {
          "FieldId": "NoGroup.NoCategory.PhiThue.AddressCustomer",
          "FieldName": "Address Customer",
          "IsMultiValue": false,
          "Type": "Address",
          "DeriveFieldsFormat": "",
          "Components": [],
          "SetValues": [],
          "Metadata": [
            {
              "Key": "Color",
              "Value": "#2bdaca"
            },
            {
              "Key": "Hotkey",
              "Value": "c"
            }
          ],
          "RuleSet": null
        },
        {
          "FieldId": "NoGroup.NoCategory.PhiThue.PaymentTotal",
          "FieldName": "Payment Total",
          "IsMultiValue": false,
          "Type": "Number",
          "DeriveFieldsFormat": "",
          "Components": [],
          "SetValues": [],
          "Metadata": [
            {
              "Key": "Color",
              "Value": "#a4b266"
            },
            {
              "Key": "Hotkey",
              "Value": "y"
            }
          ],
          "RuleSet": null
        },
        {
          "FieldId": "NoGroup.NoCategory.PhiThue.SignaturevalidIssued",
          "FieldName": "Signature valid Issued",
          "IsMultiValue": false,
          "Type": "Boolean",
          "DeriveFieldsFormat": "",
          "Components": [],
          "SetValues": [],
          "Metadata": [
            {
              "Key": "Color",
              "Value": "#91c2d7"
            },
            {
              "Key": "Hotkey",
              "Value": "g"
            }
          ],
          "RuleSet": null
        }
      ]
    },
    {
      "DocumentTypeId": "NoGroup.NoCategory.BenhVien",
      "Group": "",
      "Category": "",
      "Name": "BenhVien",
      "OptionalUniqueIdentifier": "",
      "TypeField": {
        "FieldId": "NoGroup.NoCategory.BenhVien.DocumentType",
        "FieldName": "Document Type"
      },
      "Fields": [
        {
          "FieldId": "NoGroup.NoCategory.BenhVien.Form",
          "FieldName": "Form",
          "IsMultiValue": false,
          "Type": "Text",
          "DeriveFieldsFormat": "",
          "Components": [],
          "SetValues": [],
          "Metadata": [
            {
              "Key": "Color",
              "Value": "#038a18"
            },
            {
              "Key": "Hotkey",
              "Value": "r"
            }
          ],
          "RuleSet": null
        },
        {
          "FieldId": "NoGroup.NoCategory.BenhVien.Serial",
          "FieldName": "Serial",
          "IsMultiValue": false,
          "Type": "Text",
          "DeriveFieldsFormat": "",
          "Components": [],
          "SetValues": [],
          "Metadata": [
            {
              "Key": "Color",
              "Value": "#fa6616"
            },
            {
              "Key": "Hotkey",
              "Value": "e"
            }
          ],
          "RuleSet": null
        },
        {
          "FieldId": "NoGroup.NoCategory.BenhVien.No",
          "FieldName": "No.",
          "IsMultiValue": false,
          "Type": "Text",
          "DeriveFieldsFormat": "",
          "Components": [],
          "SetValues": [],
          "Metadata": [
            {
              "Key": "Color",
              "Value": "#8a97a0"
            },
            {
              "Key": "Hotkey",
              "Value": "q"
            }
          ],
          "RuleSet": null
        },
        {
          "FieldId": "NoGroup.NoCategory.BenhVien.NameCustomer",
          "FieldName": "Name Customer",
          "IsMultiValue": false,
          "Type": "Text",
          "DeriveFieldsFormat": "",
          "Components": [],
          "SetValues": [],
          "Metadata": [
            {
              "Key": "Color",
              "Value": "#957352"
            },
            {
              "Key": "Hotkey",
              "Value": "y"
            }
          ],
          "RuleSet": null
        },
        {
          "FieldId": "NoGroup.NoCategory.BenhVien.TaxCodeCustomer",
          "FieldName": "Tax Code Customer",
          "IsMultiValue": false,
          "Type": "Text",
          "DeriveFieldsFormat": "",
          "Components": [],
          "SetValues": [],
          "Metadata": [
            {
              "Key": "Color",
              "Value": "#d27db4"
            },
            {
              "Key": "Hotkey",
              "Value": "j"
            }
          ],
          "RuleSet": null
        },
        {
          "FieldId": "NoGroup.NoCategory.BenhVien.AddressCustomer",
          "FieldName": "Address Customer",
          "IsMultiValue": false,
          "Type": "Address",
          "DeriveFieldsFormat": "",
          "Components": [],
          "SetValues": [],
          "Metadata": [
            {
              "Key": "Color",
              "Value": "#b600ff"
            },
            {
              "Key": "Hotkey",
              "Value": "v"
            }
          ],
          "RuleSet": null
        },
        {
          "FieldId": "NoGroup.NoCategory.BenhVien.PaymnentTotal",
          "FieldName": "Paymnent Total",
          "IsMultiValue": false,
          "Type": "Number",
          "DeriveFieldsFormat": "",
          "Components": [],
          "SetValues": [],
          "Metadata": [
            {
              "Key": "Color",
              "Value": "#1c70f1"
            },
            {
              "Key": "Hotkey",
              "Value": "2"
            }
          ],
          "RuleSet": null
        },
        {
          "FieldId": "NoGroup.NoCategory.BenhVien.SignaturevalidIssued",
          "FieldName": "Signature valid Issued",
          "IsMultiValue": false,
          "Type": "Boolean",
          "DeriveFieldsFormat": "",
          "Components": [],
          "SetValues": [],
          "Metadata": [
            {
              "Key": "RequiresReference",
              "Value": "False"
            },
            {
              "Key": "Color",
              "Value": "#6d759e"
            },
            {
              "Key": "Hotkey",
              "Value": "3"
            }
          ],
          "RuleSet": null
        }
      ]
    },
    {
      "DocumentTypeId": "NoGroup.NoCategory.BanHang",
      "Group": "",
      "Category": "",
      "Name": "BanHang",
      "OptionalUniqueIdentifier": "",
      "TypeField": {
        "FieldId": "NoGroup.NoCategory.BanHang.DocumentType",
        "FieldName": "Document Type"
      },
      "Fields": [
        {
          "FieldId": "NoGroup.NoCategory.BanHang.Form",
          "FieldName": "Form ",
          "IsMultiValue": false,
          "Type": "Text",
          "DeriveFieldsFormat": "",
          "Components": [],
          "SetValues": [],
          "Metadata": [
            {
              "Key": "Color",
              "Value": "#038a18"
            },
            {
              "Key": "Hotkey",
              "Value": "r"
            }
          ],
          "RuleSet": null
        },
        {
          "FieldId": "NoGroup.NoCategory.BanHang.Serial",
          "FieldName": "Serial",
          "IsMultiValue": false,
          "Type": "Text",
          "DeriveFieldsFormat": "",
          "Components": [],
          "SetValues": [],
          "Metadata": [
            {
              "Key": "Color",
              "Value": "#fa6616"
            },
            {
              "Key": "Hotkey",
              "Value": "e"
            }
          ],
          "RuleSet": null
        },
        {
          "FieldId": "NoGroup.NoCategory.BanHang.No",
          "FieldName": "No.",
          "IsMultiValue": false,
          "Type": "Text",
          "DeriveFieldsFormat": "",
          "Components": [],
          "SetValues": [],
          "Metadata": [
            {
              "Key": "Color",
              "Value": "#8a97a0"
            },
            {
              "Key": "Hotkey",
              "Value": "q"
            }
          ],
          "RuleSet": null
        },
        {
          "FieldId": "NoGroup.NoCategory.BanHang.NameCustomer",
          "FieldName": "Name Customer",
          "IsMultiValue": false,
          "Type": "Text",
          "DeriveFieldsFormat": "",
          "Components": [],
          "SetValues": [],
          "Metadata": [
            {
              "Key": "Color",
              "Value": "#2babff"
            },
            {
              "Key": "Hotkey",
              "Value": "y"
            }
          ],
          "RuleSet": null
        },
        {
          "FieldId": "NoGroup.NoCategory.BanHang.CompanyCustomer",
          "FieldName": "Company Customer",
          "IsMultiValue": false,
          "Type": "Text",
          "DeriveFieldsFormat": "",
          "Components": [],
          "SetValues": [],
          "Metadata": [
            {
              "Key": "Color",
              "Value": "#9600e5"
            },
            {
              "Key": "Hotkey",
              "Value": "g"
            }
          ],
          "RuleSet": null
        },
        {
          "FieldId": "NoGroup.NoCategory.BanHang.TaxcodeCustomer",
          "FieldName": "Tax code Customer",
          "IsMultiValue": false,
          "Type": "Text",
          "DeriveFieldsFormat": "",
          "Components": [],
          "SetValues": [],
          "Metadata": [
            {
              "Key": "Color",
              "Value": "#75b597"
            },
            {
              "Key": "Hotkey",
              "Value": "j"
            }
          ],
          "RuleSet": null
        },
        {
          "FieldId": "NoGroup.NoCategory.BanHang.AddressCustomer",
          "FieldName": "Address Customer",
          "IsMultiValue": false,
          "Type": "Address",
          "DeriveFieldsFormat": "",
          "Components": [],
          "SetValues": [],
          "Metadata": [
            {
              "Key": "Color",
              "Value": "#ef15ee"
            },
            {
              "Key": "Hotkey",
              "Value": "z"
            }
          ],
          "RuleSet": null
        },
        {
          "FieldId": "NoGroup.NoCategory.BanHang.PaymentTotal",
          "FieldName": "Payment Total",
          "IsMultiValue": false,
          "Type": "Number",
          "DeriveFieldsFormat": "",
          "Components": [],
          "SetValues": [],
          "Metadata": [
            {
              "Key": "Color",
              "Value": "#b9b466"
            },
            {
              "Key": "Hotkey",
              "Value": "1"
            }
          ],
          "RuleSet": null
        },
        {
          "FieldId": "NoGroup.NoCategory.BanHang.SignaturevalidIssued",
          "FieldName": "Signature valid Issued",
          "IsMultiValue": false,
          "Type": "Boolean",
          "DeriveFieldsFormat": "",
          "Components": [],
          "SetValues": [],
          "Metadata": [
            {
              "Key": "Color",
              "Value": "#60b6e2"
            },
            {
              "Key": "Hotkey",
              "Value": "2"
            }
          ],
          "RuleSet": null
        }
      ]
    },
    {
      "DocumentTypeId": "NoGroup.NoCategory.VeSinh",
      "Group": "",
      "Category": "",
      "Name": "VeSinh",
      "OptionalUniqueIdentifier": "",
      "TypeField": {
        "FieldId": "NoGroup.NoCategory.VeSinh.DocumentType",
        "FieldName": "Document Type"
      },
      "Fields": [
        {
          "FieldId": "NoGroup.NoCategory.VeSinh.Form",
          "FieldName": "Form",
          "IsMultiValue": false,
          "Type": "Text",
          "DeriveFieldsFormat": "",
          "Components": [],
          "SetValues": [],
          "Metadata": [
            {
              "Key": "Color",
              "Value": "#038a18"
            },
            {
              "Key": "Hotkey",
              "Value": "r"
            }
          ],
          "RuleSet": null
        },
        {
          "FieldId": "NoGroup.NoCategory.VeSinh.Serial",
          "FieldName": "Serial",
          "IsMultiValue": false,
          "Type": "Text",
          "DeriveFieldsFormat": "",
          "Components": [],
          "SetValues": [],
          "Metadata": [
            {
              "Key": "Color",
              "Value": "#fa6616"
            },
            {
              "Key": "Hotkey",
              "Value": "e"
            }
          ],
          "RuleSet": null
        },
        {
          "FieldId": "NoGroup.NoCategory.VeSinh.No",
          "FieldName": "No.",
          "IsMultiValue": false,
          "Type": "Text",
          "DeriveFieldsFormat": "",
          "Components": [],
          "SetValues": [],
          "Metadata": [
            {
              "Key": "Color",
              "Value": "#8a97a0"
            },
            {
              "Key": "Hotkey",
              "Value": "q"
            }
          ],
          "RuleSet": null
        },
        {
          "FieldId": "NoGroup.NoCategory.VeSinh.NameCustomer",
          "FieldName": "Name Customer",
          "IsMultiValue": false,
          "Type": "Text",
          "DeriveFieldsFormat": "",
          "Components": [],
          "SetValues": [],
          "Metadata": [
            {
              "Key": "Color",
              "Value": "#f3975c"
            },
            {
              "Key": "Hotkey",
              "Value": "y"
            }
          ],
          "RuleSet": null
        },
        {
          "FieldId": "NoGroup.NoCategory.VeSinh.AddressCustomer",
          "FieldName": "Address Customer",
          "IsMultiValue": false,
          "Type": "Address",
          "DeriveFieldsFormat": "",
          "Components": [],
          "SetValues": [],
          "Metadata": [
            {
              "Key": "Color",
              "Value": "#5daabb"
            },
            {
              "Key": "Hotkey",
              "Value": "g"
            }
          ],
          "RuleSet": null
        },
        {
          "FieldId": "NoGroup.NoCategory.VeSinh.Taxcode",
          "FieldName": "Tax code",
          "IsMultiValue": false,
          "Type": "Number",
          "DeriveFieldsFormat": "",
          "Components": [],
          "SetValues": [],
          "Metadata": [
            {
              "Key": "Color",
              "Value": "#9c59f8"
            },
            {
              "Key": "Hotkey",
              "Value": "x"
            }
          ],
          "RuleSet": null
        },
        {
          "FieldId": "NoGroup.NoCategory.VeSinh.PaymentTotal",
          "FieldName": "Payment Total",
          "IsMultiValue": false,
          "Type": "Number",
          "DeriveFieldsFormat": "",
          "Components": [],
          "SetValues": [],
          "Metadata": [
            {
              "Key": "Color",
              "Value": "#7e2eff"
            },
            {
              "Key": "Hotkey",
              "Value": "l"
            }
          ],
          "RuleSet": null
        },
        {
          "FieldId": "NoGroup.NoCategory.VeSinh.SignaturevalidIssued",
          "FieldName": "Signature valid Issued",
          "IsMultiValue": false,
          "Type": "Boolean",
          "DeriveFieldsFormat": "",
          "Components": [],
          "SetValues": [],
          "Metadata": [
            {
              "Key": "Color",
              "Value": "#637fa5"
            },
            {
              "Key": "Hotkey",
              "Value": "v"
            }
          ],
          "RuleSet": null
        }
      ]
    },
    {
      "DocumentTypeId": "NoGroup.NoCategory.TruongHoc",
      "Group": "",
      "Category": "",
      "Name": "TruongHoc",
      "OptionalUniqueIdentifier": "",
      "TypeField": {
        "FieldId": "NoGroup.NoCategory.TruongHoc.DocumentType",
        "FieldName": "Document Type"
      },
      "Fields": [
        {
          "FieldId": "NoGroup.NoCategory.TruongHoc.Form",
          "FieldName": "Form",
          "IsMultiValue": false,
          "Type": "Text",
          "DeriveFieldsFormat": "",
          "Components": [],
          "SetValues": [],
          "Metadata": [
            {
              "Key": "Color",
              "Value": "#038a18"
            },
            {
              "Key": "Hotkey",
              "Value": "r"
            }
          ],
          "RuleSet": null
        },
        {
          "FieldId": "NoGroup.NoCategory.TruongHoc.Serial",
          "FieldName": "Serial",
          "IsMultiValue": false,
          "Type": "Text",
          "DeriveFieldsFormat": "",
          "Components": [],
          "SetValues": [],
          "Metadata": [
            {
              "Key": "Color",
              "Value": "#fa6616"
            },
            {
              "Key": "Hotkey",
              "Value": "e"
            }
          ],
          "RuleSet": null
        },
        {
          "FieldId": "NoGroup.NoCategory.TruongHoc.No",
          "FieldName": "No.",
          "IsMultiValue": false,
          "Type": "Text",
          "DeriveFieldsFormat": "",
          "Components": [],
          "SetValues": [],
          "Metadata": [
            {
              "Key": "Color",
              "Value": "#8a97a0"
            },
            {
              "Key": "Hotkey",
              "Value": "q"
            }
          ],
          "RuleSet": null
        },
        {
          "FieldId": "NoGroup.NoCategory.TruongHoc.NameCustomer",
          "FieldName": "Name Customer",
          "IsMultiValue": false,
          "Type": "Text",
          "DeriveFieldsFormat": "",
          "Components": [],
          "SetValues": [],
          "Metadata": [
            {
              "Key": "Color",
              "Value": "#b6c597"
            },
            {
              "Key": "Hotkey",
              "Value": "y"
            }
          ],
          "RuleSet": null
        },
        {
          "FieldId": "NoGroup.NoCategory.TruongHoc.TaxCodeCustomer",
          "FieldName": "Tax Code Customer",
          "IsMultiValue": false,
          "Type": "Text",
          "DeriveFieldsFormat": "",
          "Components": [],
          "SetValues": [],
          "Metadata": [
            {
              "Key": "Color",
              "Value": "#a272ee"
            },
            {
              "Key": "Hotkey",
              "Value": "j"
            }
          ],
          "RuleSet": null
        },
        {
          "FieldId": "NoGroup.NoCategory.TruongHoc.AddressCustomer",
          "FieldName": "Address Customer",
          "IsMultiValue": false,
          "Type": "Address",
          "DeriveFieldsFormat": "",
          "Components": [],
          "SetValues": [],
          "Metadata": [
            {
              "Key": "Color",
              "Value": "#4a6ed2"
            },
            {
              "Key": "Hotkey",
              "Value": "v"
            }
          ],
          "RuleSet": null
        },
        {
          "FieldId": "NoGroup.NoCategory.TruongHoc.PaymentTotal",
          "FieldName": "Payment Total",
          "IsMultiValue": false,
          "Type": "Number",
          "DeriveFieldsFormat": "",
          "Components": [],
          "SetValues": [],
          "Metadata": [
            {
              "Key": "Color",
              "Value": "#9944c2"
            },
            {
              "Key": "Hotkey",
              "Value": "2"
            }
          ],
          "RuleSet": null
        },
        {
          "FieldId": "NoGroup.NoCategory.TruongHoc.SignaturevalidIssued",
          "FieldName": "Signature valid Issued",
          "IsMultiValue": false,
          "Type": "Boolean",
          "DeriveFieldsFormat": "",
          "Components": [],
          "SetValues": [],
          "Metadata": [
            {
              "Key": "Color",
              "Value": "#eb40ff"
            },
            {
              "Key": "Hotkey",
              "Value": "3"
            }
          ],
          "RuleSet": null
        }
      ]
    },
    {
      "DocumentTypeId": "NoGroup.NoCategory.Dien",
      "Group": "",
      "Category": "",
      "Name": "Dien",
      "OptionalUniqueIdentifier": "",
      "TypeField": {
        "FieldId": "NoGroup.NoCategory.Dien.DocumentType",
        "FieldName": "Document Type"
      },
      "Fields": [
        {
          "FieldId": "NoGroup.NoCategory.Dien.Form",
          "FieldName": "Form",
          "IsMultiValue": false,
          "Type": "Text",
          "DeriveFieldsFormat": "",
          "Components": [],
          "SetValues": [],
          "Metadata": [
            {
              "Key": "Color",
              "Value": "#038a18"
            },
            {
              "Key": "Hotkey",
              "Value": "r"
            }
          ],
          "RuleSet": null
        },
        {
          "FieldId": "NoGroup.NoCategory.Dien.Serial",
          "FieldName": "Serial",
          "IsMultiValue": false,
          "Type": "Text",
          "DeriveFieldsFormat": "",
          "Components": [],
          "SetValues": [],
          "Metadata": [
            {
              "Key": "Color",
              "Value": "#fa6616"
            },
            {
              "Key": "Hotkey",
              "Value": "e"
            }
          ],
          "RuleSet": null
        },
        {
          "FieldId": "NoGroup.NoCategory.Dien.No",
          "FieldName": "No.",
          "IsMultiValue": false,
          "Type": "Text",
          "DeriveFieldsFormat": "",
          "Components": [],
          "SetValues": [],
          "Metadata": [
            {
              "Key": "Color",
              "Value": "#8a97a0"
            },
            {
              "Key": "Hotkey",
              "Value": "q"
            }
          ],
          "RuleSet": null
        },
        {
          "FieldId": "NoGroup.NoCategory.Dien.NameCustomer",
          "FieldName": "Name Customer",
          "IsMultiValue": false,
          "Type": "Text",
          "DeriveFieldsFormat": "",
          "Components": [],
          "SetValues": [],
          "Metadata": [
            {
              "Key": "Color",
              "Value": "#fca027"
            },
            {
              "Key": "Hotkey",
              "Value": "w"
            }
          ],
          "RuleSet": null
        },
        {
          "FieldId": "NoGroup.NoCategory.Dien.TaxcodeCustomer",
          "FieldName": "Tax code Customer",
          "IsMultiValue": false,
          "Type": "Number",
          "DeriveFieldsFormat": "",
          "Components": [],
          "SetValues": [],
          "Metadata": [
            {
              "Key": "Color",
              "Value": "#661595"
            },
            {
              "Key": "Hotkey",
              "Value": "a"
            }
          ],
          "RuleSet": null
        },
        {
          "FieldId": "NoGroup.NoCategory.Dien.AddressCustomer",
          "FieldName": "Address Customer",
          "IsMultiValue": false,
          "Type": "Address",
          "DeriveFieldsFormat": "",
          "Components": [],
          "SetValues": [],
          "Metadata": [
            {
              "Key": "Color",
              "Value": "#8c357a"
            },
            {
              "Key": "Hotkey",
              "Value": "y"
            }
          ],
          "RuleSet": null
        },
        {
          "FieldId": "NoGroup.NoCategory.Dien.Payment",
          "FieldName": "Payment",
          "IsMultiValue": false,
          "Type": "Number",
          "DeriveFieldsFormat": "",
          "Components": [],
          "SetValues": [],
          "Metadata": [
            {
              "Key": "Color",
              "Value": "#c8ba6b"
            },
            {
              "Key": "Hotkey",
              "Value": "g"
            }
          ],
          "RuleSet": null
        },
        {
          "FieldId": "NoGroup.NoCategory.Dien.AmountVATTax",
          "FieldName": "Amount VAT Tax",
          "IsMultiValue": false,
          "Type": "Number",
          "DeriveFieldsFormat": "",
          "Components": [],
          "SetValues": [],
          "Metadata": [
            {
              "Key": "Color",
              "Value": "#22dfff"
            },
            {
              "Key": "Hotkey",
              "Value": "h"
            }
          ],
          "RuleSet": null
        },
        {
          "FieldId": "NoGroup.NoCategory.Dien.PaymentTotal",
          "FieldName": "Payment Total",
          "IsMultiValue": false,
          "Type": "Number",
          "DeriveFieldsFormat": "",
          "Components": [],
          "SetValues": [],
          "Metadata": [
            {
              "Key": "Color",
              "Value": "#c374ea"
            },
            {
              "Key": "Hotkey",
              "Value": "l"
            }
          ],
          "RuleSet": null
        },
        {
          "FieldId": "NoGroup.NoCategory.Dien.SignaturevalidIssued",
          "FieldName": "Signature valid Issued",
          "IsMultiValue": false,
          "Type": "Boolean",
          "DeriveFieldsFormat": "",
          "Components": [],
          "SetValues": [],
          "Metadata": [
            {
              "Key": "Color",
              "Value": "#a2a4d7"
            },
            {
              "Key": "Hotkey",
              "Value": "j"
            }
          ],
          "RuleSet": null
        }
      ]
    },
    {
      "DocumentTypeId": "NoGroup.NoCategory.Nuoc",
      "Group": "",
      "Category": "",
      "Name": "Nuoc",
      "OptionalUniqueIdentifier": "",
      "TypeField": {
        "FieldId": "NoGroup.NoCategory.Nuoc.DocumentType",
        "FieldName": "Document Type"
      },
      "Fields": [
        {
          "FieldId": "NoGroup.NoCategory.Nuoc.Form",
          "FieldName": "Form",
          "IsMultiValue": false,
          "Type": "Text",
          "DeriveFieldsFormat": "",
          "Components": [],
          "SetValues": [],
          "Metadata": [
            {
              "Key": "Color",
              "Value": "#038a18"
            },
            {
              "Key": "Hotkey",
              "Value": "r"
            }
          ],
          "RuleSet": null
        },
        {
          "FieldId": "NoGroup.NoCategory.Nuoc.Serial",
          "FieldName": "Serial",
          "IsMultiValue": false,
          "Type": "Text",
          "DeriveFieldsFormat": "",
          "Components": [],
          "SetValues": [],
          "Metadata": [
            {
              "Key": "Color",
              "Value": "#fa6616"
            },
            {
              "Key": "Hotkey",
              "Value": "e"
            }
          ],
          "RuleSet": null
        },
        {
          "FieldId": "NoGroup.NoCategory.Nuoc.No",
          "FieldName": "No.",
          "IsMultiValue": false,
          "Type": "Text",
          "DeriveFieldsFormat": "",
          "Components": [],
          "SetValues": [],
          "Metadata": [
            {
              "Key": "Color",
              "Value": "#8a97a0"
            },
            {
              "Key": "Hotkey",
              "Value": "q"
            }
          ],
          "RuleSet": null
        },
        {
          "FieldId": "NoGroup.NoCategory.Nuoc.NameCustomer",
          "FieldName": "Name Customer",
          "IsMultiValue": false,
          "Type": "Text",
          "DeriveFieldsFormat": "",
          "Components": [],
          "SetValues": [],
          "Metadata": [
            {
              "Key": "Color",
              "Value": "#32bead"
            },
            {
              "Key": "Hotkey",
              "Value": "g"
            }
          ],
          "RuleSet": null
        },
        {
          "FieldId": "NoGroup.NoCategory.Nuoc.TaxcodeCustomer",
          "FieldName": "Tax code Customer",
          "IsMultiValue": false,
          "Type": "Number",
          "DeriveFieldsFormat": "",
          "Components": [],
          "SetValues": [],
          "Metadata": [
            {
              "Key": "Color",
              "Value": "#8352f9"
            },
            {
              "Key": "Hotkey",
              "Value": "x"
            }
          ],
          "RuleSet": null
        },
        {
          "FieldId": "NoGroup.NoCategory.Nuoc.AddressCustomer",
          "FieldName": "Address Customer",
          "IsMultiValue": false,
          "Type": "Address",
          "DeriveFieldsFormat": "",
          "Components": [],
          "SetValues": [],
          "Metadata": [
            {
              "Key": "Color",
              "Value": "#e338fe"
            },
            {
              "Key": "Hotkey",
              "Value": "h"
            }
          ],
          "RuleSet": null
        },
        {
          "FieldId": "NoGroup.NoCategory.Nuoc.Payment",
          "FieldName": "Payment ",
          "IsMultiValue": false,
          "Type": "Number",
          "DeriveFieldsFormat": "",
          "Components": [],
          "SetValues": [],
          "Metadata": [
            {
              "Key": "Color",
              "Value": "#eccc60"
            },
            {
              "Key": "Hotkey",
              "Value": "l"
            }
          ],
          "RuleSet": null
        },
        {
          "FieldId": "NoGroup.NoCategory.Nuoc.AmountVATtax",
          "FieldName": "Amount VAT tax",
          "IsMultiValue": false,
          "Type": "Number",
          "DeriveFieldsFormat": "",
          "Components": [],
          "SetValues": [],
          "Metadata": [
            {
              "Key": "Color",
              "Value": "#eda162"
            },
            {
              "Key": "Hotkey",
              "Value": "z"
            }
          ],
          "RuleSet": null
        },
        {
          "FieldId": "NoGroup.NoCategory.Nuoc.PaymentTotal",
          "FieldName": "Payment Total",
          "IsMultiValue": false,
          "Type": "Number",
          "DeriveFieldsFormat": "",
          "Components": [],
          "SetValues": [],
          "Metadata": [
            {
              "Key": "Color",
              "Value": "#8dc2a4"
            },
            {
              "Key": "Hotkey",
              "Value": "2"
            }
          ],
          "RuleSet": null
        },
        {
          "FieldId": "NoGroup.NoCategory.Nuoc.SignaturevalidIssued",
          "FieldName": "Signature valid Issued",
          "IsMultiValue": false,
          "Type": "Boolean",
          "DeriveFieldsFormat": "",
          "Components": [],
          "SetValues": [],
          "Metadata": [
            {
              "Key": "Color",
              "Value": "#62cbfa"
            },
            {
              "Key": "Hotkey",
              "Value": "3"
            }
          ],
          "RuleSet": null
        }
      ]
    },
    {
      "DocumentTypeId": "NoGroup.NoCategory.ThueDong",
      "Group": "",
      "Category": "",
      "Name": "ThueDong",
      "OptionalUniqueIdentifier": "",
      "TypeField": {
        "FieldId": "NoGroup.NoCategory.ThueDong.DocumentType",
        "FieldName": "Document Type"
      },
      "Fields": [
        {
          "FieldId": "NoGroup.NoCategory.ThueDong.Form",
          "FieldName": "Form",
          "IsMultiValue": false,
          "Type": "Text",
          "DeriveFieldsFormat": "",
          "Components": [],
          "SetValues": [],
          "Metadata": [
            {
              "Key": "Color",
              "Value": "#038a18"
            },
            {
              "Key": "Hotkey",
              "Value": "r"
            }
          ],
          "RuleSet": null
        },
        {
          "FieldId": "NoGroup.NoCategory.ThueDong.Serial",
          "FieldName": "Serial",
          "IsMultiValue": false,
          "Type": "Text",
          "DeriveFieldsFormat": "",
          "Components": [],
          "SetValues": [],
          "Metadata": [
            {
              "Key": "Color",
              "Value": "#fa6616"
            },
            {
              "Key": "Hotkey",
              "Value": "e"
            }
          ],
          "RuleSet": null
        },
        {
          "FieldId": "NoGroup.NoCategory.ThueDong.No",
          "FieldName": "No.",
          "IsMultiValue": false,
          "Type": "Text",
          "DeriveFieldsFormat": "",
          "Components": [],
          "SetValues": [],
          "Metadata": [
            {
              "Key": "Color",
              "Value": "#8a97a0"
            },
            {
              "Key": "Hotkey",
              "Value": "q"
            }
          ],
          "RuleSet": null
        },
        {
          "FieldId": "NoGroup.NoCategory.ThueDong.NameCustomer",
          "FieldName": "Name Customer",
          "IsMultiValue": false,
          "Type": "Text",
          "DeriveFieldsFormat": "",
          "Components": [],
          "SetValues": [],
          "Metadata": [
            {
              "Key": "Color",
              "Value": "#a835ff"
            },
            {
              "Key": "Hotkey",
              "Value": "g"
            }
          ],
          "RuleSet": null
        },
        {
          "FieldId": "NoGroup.NoCategory.ThueDong.AddressCustomer",
          "FieldName": "Address Customer",
          "IsMultiValue": false,
          "Type": "Address",
          "DeriveFieldsFormat": "",
          "Components": [],
          "SetValues": [],
          "Metadata": [
            {
              "Key": "Color",
              "Value": "#b632af"
            },
            {
              "Key": "Hotkey",
              "Value": "h"
            }
          ],
          "RuleSet": null
        },
        {
          "FieldId": "NoGroup.NoCategory.ThueDong.TaxcodeCustomer",
          "FieldName": "Tax code Customer",
          "IsMultiValue": false,
          "Type": "Text",
          "DeriveFieldsFormat": "",
          "Components": [],
          "SetValues": [],
          "Metadata": [
            {
              "Key": "Color",
              "Value": "#f2ce50"
            },
            {
              "Key": "Hotkey",
              "Value": "j"
            }
          ],
          "RuleSet": null
        },
        {
          "FieldId": "NoGroup.NoCategory.ThueDong.Payment",
          "FieldName": "Payment",
          "IsMultiValue": false,
          "Type": "Number",
          "DeriveFieldsFormat": "",
          "Components": [],
          "SetValues": [],
          "Metadata": [
            {
              "Key": "Color",
              "Value": "#7f4454"
            },
            {
              "Key": "Hotkey",
              "Value": "z"
            }
          ],
          "RuleSet": null
        },
        {
          "FieldId": "NoGroup.NoCategory.ThueDong.PaymentTotal",
          "FieldName": "Payment Total",
          "IsMultiValue": false,
          "Type": "Number",
          "DeriveFieldsFormat": "",
          "Components": [],
          "SetValues": [],
          "Metadata": [
            {
              "Key": "Color",
              "Value": "#a29ab0"
            },
            {
              "Key": "Hotkey",
              "Value": "1"
            }
          ],
          "RuleSet": null
        },
        {
          "FieldId": "NoGroup.NoCategory.ThueDong.SignaturevalidIssued",
          "FieldName": "Signature valid Issued",
          "IsMultiValue": false,
          "Type": "Boolean",
          "DeriveFieldsFormat": "",
          "Components": [],
          "SetValues": [],
          "Metadata": [
            {
              "Key": "Color",
              "Value": "#a6be7c"
            },
            {
              "Key": "Hotkey",
              "Value": "2"
            }
          ],
          "RuleSet": null
        }
      ]
    },
    {
      "DocumentTypeId": "NoGroup.NoCategory.ChietKhauSauThue",
      "Group": "",
      "Category": "",
      "Name": "ChietKhauSauThue",
      "OptionalUniqueIdentifier": "",
      "TypeField": {
        "FieldId": "NoGroup.NoCategory.ChietKhauSauThue.DocumentType",
        "FieldName": "Document Type"
      },
      "Fields": [
        {
          "FieldId": "NoGroup.NoCategory.ChietKhauSauThue.Form",
          "FieldName": "Form",
          "IsMultiValue": false,
          "Type": "Text",
          "DeriveFieldsFormat": "",
          "Components": [],
          "SetValues": [],
          "Metadata": [
            {
              "Key": "Color",
              "Value": "#038a18"
            },
            {
              "Key": "Hotkey",
              "Value": "r"
            }
          ],
          "RuleSet": null
        },
        {
          "FieldId": "NoGroup.NoCategory.ChietKhauSauThue.Serial",
          "FieldName": "Serial",
          "IsMultiValue": false,
          "Type": "Text",
          "DeriveFieldsFormat": "",
          "Components": [],
          "SetValues": [],
          "Metadata": [
            {
              "Key": "Color",
              "Value": "#fa6616"
            },
            {
              "Key": "Hotkey",
              "Value": "e"
            }
          ],
          "RuleSet": null
        },
        {
          "FieldId": "NoGroup.NoCategory.ChietKhauSauThue.No",
          "FieldName": "No.",
          "IsMultiValue": false,
          "Type": "Text",
          "DeriveFieldsFormat": "",
          "Components": [],
          "SetValues": [],
          "Metadata": [
            {
              "Key": "Color",
              "Value": "#8a97a0"
            },
            {
              "Key": "Hotkey",
              "Value": "q"
            }
          ],
          "RuleSet": null
        },
        {
          "FieldId": "NoGroup.NoCategory.ChietKhauSauThue.NameCustomer",
          "FieldName": "Name Customer",
          "IsMultiValue": false,
          "Type": "Text",
          "DeriveFieldsFormat": "",
          "Components": [],
          "SetValues": [],
          "Metadata": [
            {
              "Key": "Color",
              "Value": "#6eb4c1"
            },
            {
              "Key": "Hotkey",
              "Value": "g"
            }
          ],
          "RuleSet": null
        },
        {
          "FieldId": "NoGroup.NoCategory.ChietKhauSauThue.TaxcodeCustomer",
          "FieldName": "Tax code Customer",
          "IsMultiValue": false,
          "Type": "Text",
          "DeriveFieldsFormat": "",
          "Components": [],
          "SetValues": [],
          "Metadata": [
            {
              "Key": "Color",
              "Value": "#9032a3"
            },
            {
              "Key": "Hotkey",
              "Value": "j"
            }
          ],
          "RuleSet": null
        },
        {
          "FieldId": "NoGroup.NoCategory.ChietKhauSauThue.AddressCustomer",
          "FieldName": "Address Customer",
          "IsMultiValue": false,
          "Type": "Address",
          "DeriveFieldsFormat": "",
          "Components": [],
          "SetValues": [],
          "Metadata": [
            {
              "Key": "Color",
              "Value": "#48b6aa"
            },
            {
              "Key": "Hotkey",
              "Value": "h"
            }
          ],
          "RuleSet": null
        },
        {
          "FieldId": "NoGroup.NoCategory.ChietKhauSauThue.TotalAmount",
          "FieldName": "Total Amount",
          "IsMultiValue": false,
          "Type": "Number",
          "DeriveFieldsFormat": "",
          "Components": [],
          "SetValues": [],
          "Metadata": [
            {
              "Key": "Color",
              "Value": "#b0e222"
            },
            {
              "Key": "Hotkey",
              "Value": "z"
            }
          ],
          "RuleSet": null
        },
        {
          "FieldId": "NoGroup.NoCategory.ChietKhauSauThue.PaymentTotal",
          "FieldName": "Payment Total",
          "IsMultiValue": false,
          "Type": "Number",
          "DeriveFieldsFormat": "",
          "Components": [],
          "SetValues": [],
          "Metadata": [
            {
              "Key": "Color",
              "Value": "#876b60"
            },
            {
              "Key": "Hotkey",
              "Value": "2"
            }
          ],
          "RuleSet": null
        },
        {
          "FieldId": "NoGroup.NoCategory.ChietKhauSauThue.SignatureValidIssued",
          "FieldName": "Signature Valid Issued",
          "IsMultiValue": false,
          "Type": "Boolean",
          "DeriveFieldsFormat": "",
          "Components": [],
          "SetValues": [],
          "Metadata": [
            {
              "Key": "Color",
              "Value": "#b288e0"
            },
            {
              "Key": "Hotkey",
              "Value": "3"
            }
          ],
          "RuleSet": null
        }
      ]
    },
    {
      "DocumentTypeId": "NoGroup.NoCategory.ChietKhauTruocThue",
      "Group": "",
      "Category": "",
      "Name": "ChietKhauTruocThue",
      "OptionalUniqueIdentifier": "",
      "TypeField": {
        "FieldId": "NoGroup.NoCategory.ChietKhauTruocThue.DocumentType",
        "FieldName": "Document Type"
      },
      "Fields": [
        {
          "FieldId": "NoGroup.NoCategory.ChietKhauTruocThue.Form",
          "FieldName": "Form",
          "IsMultiValue": false,
          "Type": "Text",
          "DeriveFieldsFormat": "",
          "Components": [],
          "SetValues": [],
          "Metadata": [
            {
              "Key": "Color",
              "Value": "#038a18"
            },
            {
              "Key": "Hotkey",
              "Value": "r"
            }
          ],
          "RuleSet": null
        },
        {
          "FieldId": "NoGroup.NoCategory.ChietKhauTruocThue.Serial",
          "FieldName": "Serial",
          "IsMultiValue": false,
          "Type": "Text",
          "DeriveFieldsFormat": "",
          "Components": [],
          "SetValues": [],
          "Metadata": [
            {
              "Key": "Color",
              "Value": "#fa6616"
            },
            {
              "Key": "Hotkey",
              "Value": "e"
            }
          ],
          "RuleSet": null
        },
        {
          "FieldId": "NoGroup.NoCategory.ChietKhauTruocThue.No",
          "FieldName": "No.",
          "IsMultiValue": false,
          "Type": "Text",
          "DeriveFieldsFormat": "",
          "Components": [],
          "SetValues": [],
          "Metadata": [
            {
              "Key": "Color",
              "Value": "#8a97a0"
            },
            {
              "Key": "Hotkey",
              "Value": "q"
            }
          ],
          "RuleSet": null
        },
        {
          "FieldId": "NoGroup.NoCategory.ChietKhauTruocThue.NameCustomer",
          "FieldName": "Name Customer",
          "IsMultiValue": false,
          "Type": "Text",
          "DeriveFieldsFormat": "",
          "Components": [],
          "SetValues": [],
          "Metadata": [
            {
              "Key": "Color",
              "Value": "#2be19f"
            },
            {
              "Key": "Hotkey",
              "Value": "g"
            }
          ],
          "RuleSet": null
        },
        {
          "FieldId": "NoGroup.NoCategory.ChietKhauTruocThue.AddressCustomer",
          "FieldName": "Address Customer",
          "IsMultiValue": false,
          "Type": "Address",
          "DeriveFieldsFormat": "",
          "Components": [],
          "SetValues": [],
          "Metadata": [
            {
              "Key": "Color",
              "Value": "#1c54f1"
            },
            {
              "Key": "Hotkey",
              "Value": "h"
            }
          ],
          "RuleSet": null
        },
        {
          "FieldId": "NoGroup.NoCategory.ChietKhauTruocThue.TaxcodeCustomer",
          "FieldName": "Tax code Customer",
          "IsMultiValue": false,
          "Type": "Text",
          "DeriveFieldsFormat": "",
          "Components": [],
          "SetValues": [],
          "Metadata": [
            {
              "Key": "Color",
              "Value": "#a6849a"
            },
            {
              "Key": "Hotkey",
              "Value": "j"
            }
          ],
          "RuleSet": null
        },
        {
          "FieldId": "NoGroup.NoCategory.ChietKhauTruocThue.TotalAmount",
          "FieldName": "Total Amount",
          "IsMultiValue": false,
          "Type": "Number",
          "DeriveFieldsFormat": "",
          "Components": [],
          "SetValues": [],
          "Metadata": [
            {
              "Key": "Color",
              "Value": "#e01cd9"
            },
            {
              "Key": "Hotkey",
              "Value": "z"
            }
          ],
          "RuleSet": null
        },
        {
          "FieldId": "NoGroup.NoCategory.ChietKhauTruocThue.PaymentTotal",
          "FieldName": "Payment Total",
          "IsMultiValue": false,
          "Type": "Number",
          "DeriveFieldsFormat": "",
          "Components": [],
          "SetValues": [],
          "Metadata": [
            {
              "Key": "Color",
              "Value": "#cd6def"
            },
            {
              "Key": "Hotkey",
              "Value": "2"
            }
          ],
          "RuleSet": null
        },
        {
          "FieldId": "NoGroup.NoCategory.ChietKhauTruocThue.SignatureValidIssued",
          "FieldName": "Signature Valid Issued",
          "IsMultiValue": false,
          "Type": "Boolean",
          "DeriveFieldsFormat": "",
          "Components": [],
          "SetValues": [],
          "Metadata": [
            {
              "Key": "Color",
              "Value": "#9faad2"
            },
            {
              "Key": "Hotkey",
              "Value": "3"
            }
          ],
          "RuleSet": null
        }
      ]
    },
    {
      "DocumentTypeId": "NoGroup.NoCategory.ThueTong",
      "Group": "",
      "Category": "",
      "Name": "ThueTong",
      "OptionalUniqueIdentifier": "",
      "TypeField": {
        "FieldId": "NoGroup.NoCategory.ThueTong.DocumentType",
        "FieldName": "Document Type"
      },
      "Fields": [
        {
          "FieldId": "NoGroup.NoCategory.ThueTong.Form",
          "FieldName": "Form",
          "IsMultiValue": false,
          "Type": "Text",
          "DeriveFieldsFormat": "",
          "Components": [],
          "SetValues": [],
          "Metadata": [
            {
              "Key": "Color",
              "Value": "#038a18"
            },
            {
              "Key": "Hotkey",
              "Value": "r"
            }
          ],
          "RuleSet": null
        },
        {
          "FieldId": "NoGroup.NoCategory.ThueTong.Serial",
          "FieldName": "Serial",
          "IsMultiValue": false,
          "Type": "Text",
          "DeriveFieldsFormat": "",
          "Components": [],
          "SetValues": [],
          "Metadata": [
            {
              "Key": "Color",
              "Value": "#fa6616"
            },
            {
              "Key": "Hotkey",
              "Value": "e"
            }
          ],
          "RuleSet": null
        },
        {
          "FieldId": "NoGroup.NoCategory.ThueTong.No",
          "FieldName": "No.",
          "IsMultiValue": false,
          "Type": "Text",
          "DeriveFieldsFormat": "",
          "Components": [],
          "SetValues": [],
          "Metadata": [
            {
              "Key": "Color",
              "Value": "#8a97a0"
            },
            {
              "Key": "Hotkey",
              "Value": "q"
            }
          ],
          "RuleSet": null
        },
        {
          "FieldId": "NoGroup.NoCategory.ThueTong.NameCustomer",
          "FieldName": "Name Customer",
          "IsMultiValue": false,
          "Type": "Text",
          "DeriveFieldsFormat": "",
          "Components": [],
          "SetValues": [],
          "Metadata": [
            {
              "Key": "Color",
              "Value": "#a215c0"
            },
            {
              "Key": "Hotkey",
              "Value": "y"
            }
          ],
          "RuleSet": null
        },
        {
          "FieldId": "NoGroup.NoCategory.ThueTong.TaxcodeCustomer",
          "FieldName": "Tax code Customer",
          "IsMultiValue": false,
          "Type": "Text",
          "DeriveFieldsFormat": "",
          "Components": [],
          "SetValues": [],
          "Metadata": [
            {
              "Key": "Color",
              "Value": "#e962b3"
            },
            {
              "Key": "Hotkey",
              "Value": "h"
            }
          ],
          "RuleSet": null
        },
        {
          "FieldId": "NoGroup.NoCategory.ThueTong.AddressCustomer",
          "FieldName": "Address Customer",
          "IsMultiValue": false,
          "Type": "Address",
          "DeriveFieldsFormat": "",
          "Components": [],
          "SetValues": [],
          "Metadata": [
            {
              "Key": "Color",
              "Value": "#d25489"
            },
            {
              "Key": "Hotkey",
              "Value": "g"
            }
          ],
          "RuleSet": null
        },
        {
          "FieldId": "NoGroup.NoCategory.ThueTong.PaymentTotal",
          "FieldName": "Payment Total",
          "IsMultiValue": false,
          "Type": "Number",
          "DeriveFieldsFormat": "",
          "Components": [],
          "SetValues": [],
          "Metadata": [
            {
              "Key": "Color",
              "Value": "#db6560"
            },
            {
              "Key": "Hotkey",
              "Value": "l"
            }
          ],
          "RuleSet": null
        },
        {
          "FieldId": "NoGroup.NoCategory.ThueTong.SignaturevalidIssued",
          "FieldName": "Signature valid Issued",
          "IsMultiValue": false,
          "Type": "Boolean",
          "DeriveFieldsFormat": "",
          "Components": [],
          "SetValues": [],
          "Metadata": [
            {
              "Key": "Color",
              "Value": "#ea32e1"
            },
            {
              "Key": "Hotkey",
              "Value": "k"
            }
          ],
          "RuleSet": null
        }
      ]
    }
  ],
  "Groups": [],
  "SupportedLanguages": [
    {
      "Name": "Undetermined Language",
      "Code": "und"
    },
    {
      "Name": "Bulgarian",
      "Code": "bul"
    },
    {
      "Name": "Cantonese",
      "Code": "yue"
    },
    {
      "Name": "Danish",
      "Code": "dan"
    },
    {
      "Name": "Dutch",
      "Code": "nld"
    },
    {
      "Name": "English",
      "Code": "eng"
    },
    {
      "Name": "French",
      "Code": "fra"
    },
    {
      "Name": "Georgian",
      "Code": "kat"
    },
    {
      "Name": "German",
      "Code": "deu"
    },
    {
      "Name": "Greek",
      "Code": "ell"
    },
    {
      "Name": "Hebrew",
      "Code": "heb"
    },
    {
      "Name": "Hindi",
      "Code": "hin"
    },
    {
      "Name": "Italian",
      "Code": "ita"
    },
    {
      "Name": "Japanese",
      "Code": "jpn"
    },
    {
      "Name": "Korean",
      "Code": "kor"
    },
    {
      "Name": "Macedonian",
      "Code": "mkd"
    },
    {
      "Name": "Mandarin",
      "Code": "zho"
    },
    {
      "Name": "Marathi",
      "Code": "mar"
    },
    {
      "Name": "Norwegian",
      "Code": "nor"
    },
    {
      "Name": "Polish",
      "Code": "pol"
    },
    {
      "Name": "Portuguese",
      "Code": "por"
    },
    {
      "Name": "Romanian",
      "Code": "ron"
    },
    {
      "Name": "Russian",
      "Code": "rus"
    },
    {
      "Name": "Serbian",
      "Code": "srp"
    },
    {
      "Name": "Spanish",
      "Code": "spa"
    },
    {
      "Name": "Swedish",
      "Code": "swe"
    },
    {
      "Name": "Telugu",
      "Code": "tel"
    },
    {
      "Name": "Turkish",
      "Code": "tur"
    }
  ]
}